[
  {"inv":"000101","title":"Пикник на обочине","author":"Стругацкие","year":1972,"status":"В наличии"},
  {"inv":"000102","title":"Мастер и Маргарита","author":"Булгаков","year":1967,"status":"В наличии"},
  {"inv":"000103","title":"1984","author":"Оруэлл","year":1949,"status":"На руках"},
  {"inv":"000104","title":"Граф Монте-Кристо","author":"Дюма","year":1844,"status":"В наличии"},
  {"inv":"000105","title":"Анна Каренина","author":"Толстой","year":1877,"status":"В наличии"},
  {"inv":"000106","title":"Чистый код","author":"Мартин","year":2008,"status":"В наличии"},
  {"inv":"000107","title":"Алгоритмы","author":"Кормен","year":2009,"status":"На руках"},
  {"inv":"000108","title":"Собор Парижской Богоматери","author":"Гюго","year":1831,"status":"Утеряна"},
  {"inv":"000109","title":"Война и мир","author":"Толстой","year":1869,"status":"В наличии"},
  {"inv":"000110","title":"Преступление и наказание","author":"Достоевский","year":1866,"status":"На руках"},
  {"inv":"000111","title":"Гарри Поттер и философский камень","author":"Роулинг","year":1997,"status":"В наличии"},
  {"inv":"000112","title":"Практика программирования на Java","author":"Блох","year":2001,"status":"В наличии"},
  {"inv":"000113","title":"Изучаем JavaScript","author":"Фридман","year":2018,"status":"В наличии"},
  {"inv":"000114","title":"React в действии","author":"Фрэнсис","year":2020,"status":"На руках"},
  {"inv":"000115","title":"Чистая архитектура","author":"Мартин","year":2017,"status":"В наличии"},
  {"inv":"000116","title":"Путь программиста","author":"Флэнаган","year":2012,"status":"В наличии"},
  {"inv":"000117","title":"Моби Дик","author":"Мелвилл","year":1851,"status":"В наличии"},
  {"inv":"000118","title":"Улисс","author":"Джойс","year":1922,"status":"На руках"},
  {"inv":"000119","title":"Сто лет одиночества","author":"Маркес","year":1967,"status":"В наличии"},
  {"inv":"000120","title":"Великий Гэтсби","author":"Фицджеральд","year":1925,"status":"В наличии"},
  {"inv":"000121","title":"451 градус по Фаренгейту","author":"Брэдбери","year":1953,"status":"На руках"},
  {"inv":"000122","title":"Пролетая над гнездом кукушки","author":"Кизи","year":1962,"status":"В наличии"},
  {"inv":"000123","title":"Мастер-ключ к финансам","author":"Мэннинг","year":2015,"status":"В наличии"},
  {"inv":"000124","title":"Гордость и предубеждение","author":"Остен","year":1813,"status":"В наличии"},
  {"inv":"000125","title":"Десять негритят","author":"Кристи","year":1939,"status":"На руках"},
  {"inv":"000126","title":"Братья Карамазовы","author":"Достоевский","year":1880,"status":"В наличии"},
  {"inv":"000127","title":"Над пропастью во ржи","author":"Сэлинджер","year":1951,"status":"В наличии"},
  {"inv":"000128","title":"О дивный новый мир","author":"Хаксли","year":1932,"status":"Утеряна"},
  {"inv":"000129","title":"Три товарища","author":"Ремарк","year":1936,"status":"В наличии"},
  {"inv":"000130","title":"Маленький принц","author":"Сент-Экзюпери","year":1943,"status":"На руках"},
  {"inv":"000131","title":"Графиня де Монсоро","author":"Дюма-отец","year":1846,"status":"В наличии"},
  {"inv":"000132","title":"Путь мирного воина","author":"Дэн Миллман","year":1980,"status":"В наличии"},
  {"inv":"000133","title":"Бегущий за ветром","author":"Хоссейни","year":2003,"status":"На руках"},
  {"inv":"000134","title":"Тёмные начала","author":"Голдинг","year":1954,"status":"В наличии"},
  {"inv":"000135","title":"Кодовое имя «Спутник»","author":"Смирнов","year":2019,"status":"В наличии"},
  {"inv":"000136","title":"Чёрный обелиск","author":"Ремарк","year":1956,"status":"В наличии"},
  {"inv":"000137","title":"Принц и нищий","author":"Твен","year":1881,"status":"На руках"},
  {"inv":"000138","title":"Алхимик","author":"Коэльо","year":1988,"status":"В наличии"},
  {"inv":"000139","title":"Исчезнувшая","author":"Флинн","year":2012,"status":"На руках"},
  {"inv":"000140","title":"Дюна","author":"Герберт","year":1965,"status":"В наличии"},
  {"inv":"000141","title":"Жизнь Пи","author":"Мартелл","year":2001,"status":"В наличии"},
  {"inv":"000142","title":"Код да Винчи","author":"Робертсон","year":2003,"status":"Утеряна"},
  {"inv":"000143","title":"Властелин колец: Братство кольца","author":"Толкин","year":1954,"status":"На руках"},
  {"inv":"000144","title":"Властелин колец: Две крепости","author":"Толкин","year":1954,"status":"В наличии"},
  {"inv":"000145","title":"Властелин колец: Возвращение короля","author":"Толкин","year":1955,"status":"В наличии"},
  {"inv":"000146","title":"Париж подождёт","author":"Сорентин","year":2018,"status":"В наличии"},
  {"inv":"000147","title":"Слепой убийца","author":"Этвуд","year":2000,"status":"На руках"},
  {"inv":"000148","title":"Норвежский лес","author":"Мураками","year":1987,"status":"В наличии"},
  {"inv":"000149","title":"Жизнь и судьба","author":"Гроссман","year":1980,"status":"В наличии"},
  {"inv":"000150","title":"Книжный вор","author":"Зюскинд","year":2005,"status":"В наличии"}
]
